LICENSE.txt
MANIFEST.in
README.rst
setup.py
bttf/__init__.py
bttf/_bttf.c
bttf/bytesformat.h
bttf/typehacks.h
bttf.egg-info/PKG-INFO
bttf.egg-info/SOURCES.txt
bttf.egg-info/dependency_links.txt
bttf.egg-info/top_level.txt