Metadata-Version: 1.1
Name: bttf
Version: 0.1
Summary: Brings some of the magic from the future to the past and from the past back to the future.
Home-page: https://github.com/ztane/bttf
Author: Antti Haapala
Author-email: antti.haapala@anttipatterns.com
License: UNKNOWN
Platform: UNKNOWN
Classifier: Development Status :: 3 - Alpha
Classifier: Framework :: Pyramid
Classifier: Programming Language :: Python :: Implementation :: CPython
